{
	"info": {
		"_postman_id": "32b19b23-96ff-4a52-8275-380117114412",
		"name": "Ayrotek",
		"schema": "https://schema.getpostman.com/json/collection/v2.1.0/collection.json"
	},
	"item": [
		{
			"name": "New Folder",
			"item": []
		},
		{
			"name": "GET products",
			"request": {
				"method": "GET",
				"header": [],
				"url": {
					"raw": "http://localhost:8080/api/products",
					"protocol": "http",
					"host": [
						"localhost"
					],
					"port": "8080",
					"path": [
						"api",
						"products"
					]
				}
			},
			"response": []
		},
		{
			"name": "add product",
			"request": {
				"method": "POST",
				"header": [],
				"body": {
					"mode": "raw",
					"raw": "{\r\n            \"productCode\": \"1fdsaf23g\",\r\n            \"productName\": \"arrrmut\",\r\n            \"stockQuantity\": 150,\r\n            \"unitPrice\": 50.99,\r\n            \"brandId\": {\"brandId\":2},\r\n            \"categoryId\": {\"categoryId\":2} \r\n        }",
					"options": {
						"raw": {
							"language": "json"
						}
					}
				},
				"url": {
					"raw": "http://localhost:8080/api/add",
					"protocol": "http",
					"host": [
						"localhost"
					],
					"port": "8080",
					"path": [
						"api",
						"add"
					]
				}
			},
			"response": []
		},
		{
			"name": "update product",
			"request": {
				"method": "POST",
				"header": [],
				"body": {
					"mode": "raw",
					"raw": "{\r\n        \"productId\": 9,\r\n        \"productCode\": \"1fdsaf23g\",\r\n        \"productName\": \"arrrmut23\",\r\n        \"stockQuantity\": 150,\r\n        \"unitPrice\": 50.99,\r\n        \"brandId\": {\r\n            \"brandId\": 2\r\n        },\r\n        \"categoryId\": {\r\n            \"categoryId\": 2\r\n        }\r\n    }",
					"options": {
						"raw": {
							"language": "json"
						}
					}
				},
				"url": {
					"raw": "http://localhost:8080/api/update",
					"protocol": "http",
					"host": [
						"localhost"
					],
					"port": "8080",
					"path": [
						"api",
						"update"
					]
				}
			},
			"response": []
		},
		{
			"name": "delete product",
			"request": {
				"method": "POST",
				"header": [],
				"url": {
					"raw": "http://localhost:8080/api/delete/9",
					"protocol": "http",
					"host": [
						"localhost"
					],
					"port": "8080",
					"path": [
						"api",
						"delete",
						"9"
					]
				}
			},
			"response": []
		},
		{
			"name": "get brands",
			"request": {
				"method": "GET",
				"header": [],
				"url": {
					"raw": "http://localhost:8080/api/brands",
					"protocol": "http",
					"host": [
						"localhost"
					],
					"port": "8080",
					"path": [
						"api",
						"brands"
					]
				}
			},
			"response": []
		},
		{
			"name": "add brand",
			"request": {
				"method": "POST",
				"header": [],
				"body": {
					"mode": "raw",
					"raw": "{\r\n            \r\n            \"brandName\": \"Muratti\"\r\n        }",
					"options": {
						"raw": {
							"language": "json"
						}
					}
				},
				"url": {
					"raw": "http://localhost:8080/api/add-brand",
					"protocol": "http",
					"host": [
						"localhost"
					],
					"port": "8080",
					"path": [
						"api",
						"add-brand"
					]
				}
			},
			"response": []
		},
		{
			"name": "update brand",
			"request": {
				"method": "POST",
				"header": [],
				"body": {
					"mode": "raw",
					"raw": " {\r\n        \"brandId\": 11,\r\n        \"brandName\": \"Parlament\"\r\n    }",
					"options": {
						"raw": {
							"language": "json"
						}
					}
				},
				"url": {
					"raw": "http://localhost:8080/api/update-brand",
					"protocol": "http",
					"host": [
						"localhost"
					],
					"port": "8080",
					"path": [
						"api",
						"update-brand"
					]
				}
			},
			"response": []
		},
		{
			"name": "delete brand",
			"request": {
				"method": "POST",
				"header": [],
				"url": {
					"raw": "http://localhost:8080/api/delete-brand/11",
					"protocol": "http",
					"host": [
						"localhost"
					],
					"port": "8080",
					"path": [
						"api",
						"delete-brand",
						"11"
					]
				}
			},
			"response": []
		},
		{
			"name": "get categories",
			"request": {
				"method": "GET",
				"header": [],
				"url": {
					"raw": "http://localhost:8080/api/categories",
					"protocol": "http",
					"host": [
						"localhost"
					],
					"port": "8080",
					"path": [
						"api",
						"categories"
					]
				}
			},
			"response": []
		},
		{
			"name": "add-category",
			"request": {
				"method": "POST",
				"header": [],
				"body": {
					"mode": "raw",
					"raw": " {\r\n            \r\n            \"categoryName\": \"Kadın Giyim\"\r\n        }",
					"options": {
						"raw": {
							"language": "json"
						}
					}
				},
				"url": {
					"raw": "http://localhost:8080/api/add-category",
					"protocol": "http",
					"host": [
						"localhost"
					],
					"port": "8080",
					"path": [
						"api",
						"add-category"
					]
				}
			},
			"response": []
		},
		{
			"name": "update category",
			"request": {
				"method": "POST",
				"header": [],
				"body": {
					"mode": "raw",
					"raw": " {\r\n            \"categoryId\": 4,\r\n            \"categoryName\": \"bebek Giyim\"\r\n        }",
					"options": {
						"raw": {
							"language": "json"
						}
					}
				},
				"url": {
					"raw": "http://localhost:8080/api/update-category",
					"protocol": "http",
					"host": [
						"localhost"
					],
					"port": "8080",
					"path": [
						"api",
						"update-category"
					]
				}
			},
			"response": []
		},
		{
			"name": "delete category",
			"request": {
				"method": "POST",
				"header": [],
				"url": {
					"raw": "http://localhost:8080/api/delete-category/16",
					"protocol": "http",
					"host": [
						"localhost"
					],
					"port": "8080",
					"path": [
						"api",
						"delete-category",
						"16"
					]
				}
			},
			"response": []
		}
	]
}